Health_and_Fitness_Check/Asupan_air.py
Health_and_Fitness_Check/BMI.py
Health_and_Fitness_Check/HitungKalori.py
Health_and_Fitness_Check/Kebutuhan_kalori.py
Health_and_Fitness_Check/StepToMeter.py
Health_and_Fitness_Check/ZonaDetakJantung.py
Health_and_Fitness_Check/__init__.py
HealthFitness-0.1.5.dist-info/METADATA
HealthFitness-0.1.5.dist-info/WHEEL
HealthFitness-0.1.5.dist-info/top_level.txt
HealthFitness-0.1.5.dist-info/RECORD
