Metadata-Version: 2.1
Name: HealthFitness
Version: 0.1.5
Summary: Menyediakan fitur pengecekan kesehatan dan fitness
Home-page: https://github.com/RfqiAlan/HealthFitnessCheck
Author: Kelompok 4 AP B
Author-email: rifqialan46475@gmail.com
Classifier: Programming Language :: Python :: 3
Classifier: License :: OSI Approved :: MIT License
Classifier: Operating System :: OS Independent
Requires-Python: >=3.6
